openstreetmap_downloader-1.1.3.dist-info/licenses/LICENSE
osm_downloader/__init__.py
osm_downloader/downloader.py
osm_downloader/logger.py
osm_downloader/main.py
osm_downloader/storage.py
openstreetmap_downloader-1.1.3.dist-info/METADATA
openstreetmap_downloader-1.1.3.dist-info/WHEEL
openstreetmap_downloader-1.1.3.dist-info/top_level.txt
openstreetmap_downloader-1.1.3.dist-info/RECORD
