Metadata-Version: 2.4
Name: openstreetmap-downloader
Version: 1.1.3
Summary: Downloads OpenStreetMap data by configurations
Requires-Python: >=3.11
License-File: LICENSE
Requires-Dist: boto3>=1.40.69
Requires-Dist: click>=8.2.1
Requires-Dist: fsspec>=2025.10.0
Requires-Dist: geopandas>=1.1.1
Requires-Dist: osmnx>=2.0.6
Requires-Dist: pandas>=2.3.2
Requires-Dist: python-dotenv>=1.1.1
Requires-Dist: pyyaml>=6.0.2
Dynamic: license-file
